django_middleware_public_pages-0.16.dist-info/METADATA
django_middleware_public_pages-0.16.dist-info/RECORD
django_middleware_public_pages-0.16.dist-info/WHEEL
django_middleware_public_pages-0.16.dist-info/top_level.txt
middleware_public_pages/__init__.py
middleware_public_pages/middleware.py
middleware_public_pages/middleware_public_pages.py
migrations/__init__.py
