Metadata-Version: 2.1
Name: django-middleware-public-pages
Version: 0.16
Summary: A django middleware to switch between public and protected versions of the same page (url).
Home-page: https://gitlab.com/rristow/django-middleware-public-pages
Author: Rodrigo Ristow
Author-email: rodrigo@maxttor.com
License: BSD License
Platform: UNKNOWN
Classifier: Environment :: Web Environment
Classifier: Framework :: Django
Classifier: Framework :: Django :: 1.10
Classifier: Intended Audience :: Developers
Classifier: License :: OSI Approved :: BSD License
Classifier: Operating System :: OS Independent
Classifier: Programming Language :: Python
Classifier: Programming Language :: Python :: 3.5
Classifier: Programming Language :: Python :: 3.6
Classifier: Topic :: Internet :: WWW/HTTP
Classifier: Topic :: Internet :: WWW/HTTP :: Dynamic Content
